pythingd/__base__.py
pythingd/__errors__.py
pythingd/__init__.py
pythingd/things.py
pythingd/commons/__init__.py
pythingd/commons/abstract/__init__.py
pythingd/commons/abstract/sets.py
pythingd/commons/entity/__init__.py
pythingd/commons/entity/abstract.py
pythingd/commons/entity/physical.py
pythingd/commons/entity/relations.py
pythingd/commons/foundational/__init__.py
pythingd/commons/foundational/quantity.py
pythingd/commons/foundational/space.py
pythingd/commons/foundational/time.py
pythingd/commons/truths/__init__.py
pythingd/domains/__init__.py
pythingd/domains/controller.py
pythingd/things/__init__.py
pythingd/things/library.py
pythingd/utils/__init__.py
pythingd/utils/statistical.py
pythingd/utils/utilities.py
pythingd/utils/extend/__init__.py
pythingd/utils/extend/_manager.py
pythingd/utils/extend/native/__init__.py
pythingd/utils/patterns/__init__.py
pythingd/utils/patterns/mixins.py
pythingd/utils/tools/__init__.py
pythingd/utils/tools/basic.py
pythingd-0.1.0.dist-info/LICENSE.md
pythingd-0.1.0.dist-info/METADATA
pythingd-0.1.0.dist-info/WHEEL
pythingd-0.1.0.dist-info/top_level.txt
pythingd-0.1.0.dist-info/RECORD
