Metadata-Version: 2.2
Name: pythingd
Version: 0.1.0
Summary: A PyForge project for managing Things and their relationships.
Author-email: Aidan Hogg <aidan.hogg@dirtywork.solutions>
License: # CC0 1.0 Universal
Project-URL: Homepage, https://open.dirtywork.solutions/pythingd
Project-URL: Documentation, https://open.dirtywork.solutions/pythingd/docs
Project-URL: Source, https://github.com/DirtyWork-Solutions/PyThings
Project-URL: Issues, https://github.com/DirtyWork-Solutions/PyThings/tree/main/.github/ISSUE_TEMPLATE
License-File: LICENSE.md
Requires-Dist: cachetools
Requires-Dist: pydantic
Requires-Dist: pyutile
